glean/api_client/__init__.py
glean/api_client/_hooks/__init__.py
glean/api_client/_hooks/agent_file_upload_error_hook.py
glean/api_client/_hooks/multipart_fix_hook.py
glean/api_client/_hooks/registration.py
glean/api_client/_hooks/sdkhooks.py
glean/api_client/_hooks/types.py
glean/api_client/_version.py
glean/api_client/agents.py
glean/api_client/announcements.py
glean/api_client/answers.py
glean/api_client/basesdk.py
glean/api_client/client.py
glean/api_client/client_activity.py
glean/api_client/client_authentication.py
glean/api_client/client_chat.py
glean/api_client/client_documents.py
glean/api_client/client_governance.py
glean/api_client/client_shortcuts.py
glean/api_client/client_verification.py
glean/api_client/collections.py
glean/api_client/data.py
glean/api_client/datasources.py
glean/api_client/entities.py
glean/api_client/errors/__init__.py
glean/api_client/errors/collectionerror.py
glean/api_client/errors/gleanbaseerror.py
glean/api_client/errors/gleandataerror.py
glean/api_client/errors/gleanerror.py
glean/api_client/errors/no_response_error.py
glean/api_client/errors/responsevalidationerror.py
glean/api_client/governance.py
glean/api_client/governance_documents.py
glean/api_client/httpclient.py
glean/api_client/indexing.py
glean/api_client/indexing_authentication.py
glean/api_client/indexing_datasource.py
glean/api_client/indexing_documents.py
glean/api_client/indexing_permissions.py
glean/api_client/indexing_shortcuts.py
glean/api_client/insights.py
glean/api_client/messages.py
glean/api_client/models/__init__.py
glean/api_client/models/activity.py
glean/api_client/models/activityevent.py
glean/api_client/models/activityeventparams.py
glean/api_client/models/addcollectionitemserror.py
glean/api_client/models/addcollectionitemsrequest.py
glean/api_client/models/addcollectionitemsresponse.py
glean/api_client/models/additionalfielddefinition.py
glean/api_client/models/agent.py
glean/api_client/models/agentconfig.py
glean_api_client-0.11.27.dist-info/METADATA
glean_api_client-0.11.27.dist-info/WHEEL
glean_api_client-0.11.27.dist-info/licenses/LICENSE
glean_api_client-0.11.27.dist-info/RECORD
