Metadata-Version: 2.4
Name: glean-api-client
Version: 0.11.27
Summary: Python Client SDK Generated by Speakeasy.
License-File: LICENSE
Author: Glean Technologies, Inc.
Requires-Python: >=3.9.2
Classifier: Programming Language :: Python :: 3
Classifier: Programming Language :: Python :: 3.10
Classifier: Programming Language :: Python :: 3.11
Classifier: Programming Language :: Python :: 3.12
Classifier: Programming Language :: Python :: 3.13
Classifier: Programming Language :: Python :: 3.14
Requires-Dist: httpcore (>=1.0.9)
Requires-Dist: httpx (>=0.28.1)
Requires-Dist: pydantic (>=2.11.2)
Project-URL: Repository, https://github.com/gleanwork/api-client-python.git
